{
  "main": {
    "id": "28455668e115257e",
    "type": "split",
    "children": [
      {
        "id": "ce6e4d99a96b44a8",
        "type": "tabs",
        "children": [
          {
            "id": "4014398a4fe3377c",
            "type": "leaf",
            "state": {
              "type": "markdown",
              "state": {
                "file": "Android SDK CLI tools only.md",
                "mode": "source",
                "source": false
              }
            }
          }
        ]
      }
    ],
    "direction": "vertical"
  },
  "left": {
    "id": "f9912f196cf347b3",
    "type": "split",
    "children": [
      {
        "id": "3e989b4c6c31881f",
        "type": "tabs",
        "children": [
          {
            "id": "5152b4391e815341",
            "type": "leaf",
            "state": {
              "type": "file-explorer",
              "state": {
                "sortOrder": "alphabetical"
              }
            }
          },
          {
            "id": "f4a79e1a6890d426",
            "type": "leaf",
            "state": {
              "type": "search",
              "state": {
                "query": "",
                "matchingCase": false,
                "explainSearch": false,
                "collapseAll": false,
                "extraContext": false,
                "sortOrder": "alphabetical"
              }
            }
          },
          {
            "id": "7aa750320286d597",
            "type": "leaf",
            "state": {
              "type": "bookmarks",
              "state": {}
            }
          }
        ]
      }
    ],
    "direction": "horizontal",
    "width": 300,
    "collapsed": true
  },
  "right": {
    "id": "943f4135e38f47b9",
    "type": "split",
    "children": [
      {
        "id": "0ea58e242cc3455d",
        "type": "tabs",
        "children": [
          {
            "id": "666f3ad2a0067d97",
            "type": "leaf",
            "state": {
              "type": "backlink",
              "state": {
                "file": "Android SDK CLI tools only.md",
                "collapseAll": false,
                "extraContext": false,
                "sortOrder": "alphabetical",
                "showSearch": false,
                "searchQuery": "",
                "backlinkCollapsed": false,
                "unlinkedCollapsed": true
              }
            }
          },
          {
            "id": "7571ed495d8de6e2",
            "type": "leaf",
            "state": {
              "type": "outgoing-link",
              "state": {
                "file": "Android SDK CLI tools only.md",
                "linksCollapsed": false,
                "unlinkedCollapsed": true
              }
            }
          },
          {
            "id": "8ada0b896f82e51c",
            "type": "leaf",
            "state": {
              "type": "tag",
              "state": {
                "sortOrder": "frequency",
                "useHierarchy": true
              }
            }
          },
          {
            "id": "7f1d69f2de0793e9",
            "type": "leaf",
            "state": {
              "type": "outline",
              "state": {
                "file": "Android SDK CLI tools only.md"
              }
            }
          }
        ]
      }
    ],
    "direction": "horizontal",
    "width": 300,
    "collapsed": true
  },
  "left-ribbon": {
    "hiddenItems": {
      "switcher:Open quick switcher": false,
      "graph:Open graph view": false,
      "canvas:Create new canvas": false,
      "daily-notes:Open today's daily note": false,
      "templates:Insert template": false,
      "command-palette:Open command palette": false
    }
  },
  "active": "5152b4391e815341",
  "lastOpenFiles": [
    "Japanese Input.md",
    "Useful bundles.md"
  ]
}